{
  "manifestVersion": "3.2",
  "proxies": [
    {
      "address": "0xb52BAbD89eEDBeF6242784DC5c60C1E609538D06",
      "txHash": "0x9ad91a12c5321bcdb69917f87cfac874f44da371bc2c08609adba8c49a2dbcb4",
      "kind": "uups"
    },
    {
      "address": "0x14F2f68554B60150734A96A7f91Bc37916275bF7",
      "txHash": "0x63dbe14f75c723f5cb4e870e1ecde962c44a54d083f8909d5583b72b1c1f826e",
      "kind": "uups"
    },
    {
      "address": "0xd3926BFBEC09879094d44BAA3161cB8E66397d1E",
      "txHash": "0x9a06689367b79fdd358a0bf11f7dd20a1d7aae2d8a35e0240896bc9fa4767402",
      "kind": "uups"
    },
    {
      "address": "0x30c9227Fa0b1F4bb5cbB3257F079ae774F3920e5",
      "txHash": "0xbedde9f9f0540b9421c6188307fa4b8c8af7e105d9584e04af3012df4de4b1cc",
      "kind": "uups"
    },
    {
      "address": "0xDf90a1B75626639cC33f455a65eEFbc4a98850e3",
      "txHash": "0x2fb4003b5fd0bf1a3400dfc6aea2ff3a106b437b529cb34eba3c64f0ed9b343e",
      "kind": "uups"
    },
    {
      "address": "0xec10D3cc571d312F6D6A13B5855B570D0Ebd6FDB",
      "txHash": "0x368650abf132fd95b8be4bc0598bcfbb2d5704f33c9789a80fd9e7733f4fc64f",
      "kind": "uups"
    },
    {
      "address": "0xBb9788dEad551fB6a2B64e8907dD918E8c646015",
      "txHash": "0xfa6d75811d06c075363360d372caa1f5a6af250bdb005c3ee198d0a5172fe219",
      "kind": "uups"
    },
    {
      "address": "0xE4F81A022fEF9a81Cbe3ccB1B77213043A6C073e",
      "txHash": "0x6912cdd03f05d3a86a72e487b0b8ac423e64bb7804cf425dac502a4cd9fff9bc",
      "kind": "uups"
    },
    {
      "address": "0xb98085ffBDC81206b744898ba1415F27f8155482",
      "txHash": "0xbfa894e7a60d66f7413b897c778a911229e2bf446d2ce106517c421380326453",
      "kind": "uups"
    },
    {
      "address": "0x5565a44033384022f1f47b631241bb9D0C304F71",
      "txHash": "0x21726b6b8403be4f49cd1e4b890e07c39e7977179f3ca5f5f229524db9dbbbfc",
      "kind": "uups"
    }
  ],
  "impls": {
    "634b1b13fbf255c665845a6eca2bf1e1d515fcd9233888fe3109c5d20ebdf9f5": {
      "address": "0x61a1bf98Bb8c89EE634B47C48210B5a796ad6786",
      "txHash": "0x6c667487a29b62548229288866b5355484d01eb58714790837a595de19dea735",
      "layout": {
        "solcVersion": "0.8.23",
        "storage": [],
        "types": {
          "t_address": {
            "label": "address",
            "numberOfBytes": "20"
          },
          "t_bool": {
            "label": "bool",
            "numberOfBytes": "1"
          },
          "t_bytes32": {
            "label": "bytes32",
            "numberOfBytes": "32"
          },
          "t_bytes4": {
            "label": "bytes4",
            "numberOfBytes": "4"
          },
          "t_mapping(t_address,t_struct(Access)77_storage)": {
            "label": "mapping(address => struct AccessManagerUpgradeable.Access)",
            "numberOfBytes": "32"
          },
          "t_mapping(t_address,t_struct(TargetConfig)71_storage)": {
            "label": "mapping(address => struct AccessManagerUpgradeable.TargetConfig)",
            "numberOfBytes": "32"
          },
          "t_mapping(t_bytes32,t_struct(Schedule)95_storage)": {
            "label": "mapping(bytes32 => struct AccessManagerUpgradeable.Schedule)",
            "numberOfBytes": "32"
          },
          "t_mapping(t_bytes4,t_uint64)": {
            "label": "mapping(bytes4 => uint64)",
            "numberOfBytes": "32"
          },
          "t_mapping(t_uint64,t_struct(Role)90_storage)": {
            "label": "mapping(uint64 => struct AccessManagerUpgradeable.Role)",
            "numberOfBytes": "32"
          },
          "t_struct(Access)77_storage": {
            "label": "struct AccessManagerUpgradeable.Access",
            "members": [
              {
                "label": "since",
                "type": "t_uint48",
                "offset": 0,
                "slot": "0"
              },
              {
                "label": "delay",
                "type": "t_userDefinedValueType(Delay)725",
                "offset": 6,
                "slot": "0"
              }
            ],
            "numberOfBytes": "32"
          },
          "t_struct(AccessManagerStorage)114_storage": {
            "label": "struct AccessManagerUpgradeable.AccessManagerStorage",
            "members": [
              {
                "label": "_targets",
                "type": "t_mapping(t_address,t_struct(TargetConfig)71_storage)",
                "offset": 0,
                "slot": "0"
              },
              {
                "label": "_roles",
                "type": "t_mapping(t_uint64,t_struct(Role)90_storage)",
                "offset": 0,
                "slot": "1"
              },
              {
                "label": "_schedules",
                "type": "t_mapping(t_bytes32,t_struct(Schedule)95_storage)",
                "offset": 0,
                "slot": "2"
              },
              {
                "label": "_executionId",
                "type": "t_bytes32",
                "offset": 0,
                "slot": "3"
              }
            ],
            "numberOfBytes": "128"
          },
          "t_struct(InitializableStorage)129_storage": {
            "label": "struct Initializable.InitializableStorage",
            "members": [
              {
                "label": "_initialized",
                "type": "t_uint64",
                "offset": 0,
                "slot": "0"
              },
              {
                "label": "_initializing",
                "type": "t_bool",
                "offset": 8,
                "slot": "0"
              }
            ],
            "numberOfBytes": "32"
          },
          "t_struct(Role)90_storage": {
            "label": "struct AccessManagerUpgradeable.Role",
            "members": [
              {
                "label": "members",
                "type": "t_mapping(t_address,t_struct(Access)77_storage)",
                "offset": 0,
                "slot": "0"
              },
              {
                "label": "admin",
                "type": "t_uint64",
                "offset": 0,
                "slot": "1"
              },
              {
                "label": "guardian",
                "type": "t_uint64",
                "offset": 8,
                "slot": "1"
              },
              {
                "label": "grantDelay",
                "type": "t_userDefinedValueType(Delay)725",
                "offset": 16,
                "slot": "1"
              }
            ],
            "numberOfBytes": "64"
          },
          "t_struct(Schedule)95_storage": {
            "label": "struct AccessManagerUpgradeable.Schedule",
            "members": [
              {
                "label": "timepoint",
                "type": "t_uint48",
                "offset": 0,
                "slot": "0"
              },
              {
                "label": "nonce",
                "type": "t_uint32",
                "offset": 6,
                "slot": "0"
              }
            ],
            "numberOfBytes": "32"
          },
          "t_struct(TargetConfig)71_storage": {
            "label": "struct AccessManagerUpgradeable.TargetConfig",
            "members": [
              {
                "label": "allowedRoles",
                "type": "t_mapping(t_bytes4,t_uint64)",
                "offset": 0,
                "slot": "0"
              },
              {
                "label": "adminDelay",
                "type": "t_userDefinedValueType(Delay)725",
                "offset": 0,
                "slot": "1"
              },
              {
                "label": "closed",
                "type": "t_bool",
                "offset": 14,
                "slot": "1"
              }
            ],
            "numberOfBytes": "64"
          },
          "t_uint32": {
            "label": "uint32",
            "numberOfBytes": "4"
          },
          "t_uint48": {
            "label": "uint48",
            "numberOfBytes": "6"
          },
          "t_uint64": {
            "label": "uint64",
            "numberOfBytes": "8"
          },
          "t_userDefinedValueType(Delay)725": {
            "label": "Time.Delay",
            "numberOfBytes": "14",
            "underlying": "t_uint112"
          },
          "t_uint112": {
            "label": "uint112"
          }
        },
        "namespaces": {
          "erc7201:openzeppelin.storage.AccessManager": [
            {
              "contract": "AccessManagerUpgradeable",
              "label": "_targets",
              "type": "t_mapping(t_address,t_struct(TargetConfig)71_storage)",
              "src": "@openzeppelin/contracts-upgradeable/access/manager/AccessManagerUpgradeable.sol:106",
              "offset": 0,
              "slot": "0"
            },
            {
              "contract": "AccessManagerUpgradeable",
              "label": "_roles",
              "type": "t_mapping(t_uint64,t_struct(Role)90_storage)",
              "src": "@openzeppelin/contracts-upgradeable/access/manager/AccessManagerUpgradeable.sol:107",
              "offset": 0,
              "slot": "1"
            },
            {
              "contract": "AccessManagerUpgradeable",
              "label": "_schedules",
              "type": "t_mapping(t_bytes32,t_struct(Schedule)95_storage)",
              "src": "@openzeppelin/contracts-upgradeable/access/manager/AccessManagerUpgradeable.sol:108",
              "offset": 0,
              "slot": "2"
            },
            {
              "contract": "AccessManagerUpgradeable",
              "label": "_executionId",
              "type": "t_bytes32",
              "src": "@openzeppelin/contracts-upgradeable/access/manager/AccessManagerUpgradeable.sol:112",
              "offset": 0,
              "slot": "3"
            }
          ],
          "erc7201:openzeppelin.storage.Initializable": [
            {
              "contract": "Initializable",
              "label": "_initialized",
              "type": "t_uint64",
              "src": "@openzeppelin/contracts-upgradeable/proxy/utils/Initializable.sol:69",
              "offset": 0,
              "slot": "0"
            },
            {
              "contract": "Initializable",
              "label": "_initializing",
              "type": "t_bool",
              "src": "@openzeppelin/contracts-upgradeable/proxy/utils/Initializable.sol:73",
              "offset": 8,
              "slot": "0"
            }
          ]
        }
      }
    },
    "037d43b261280f1729f7268645aa582ecd2507d23f4450ad47f44976267ed1b2": {
      "address": "0xFf38a8116C6E21886baCC8Ff0Db41D73CB955763",
      "txHash": "0xcde696b1d7ed056a55625d890574ec90a9e9e3c3143f6894ca1edbd76b35c2f0",
      "layout": {
        "solcVersion": "0.8.23",
        "storage": [
          {
            "label": "isLongPool",
            "offset": 0,
            "slot": "0",
            "type": "t_bool",
            "contract": "BaseWasabiPool",
            "src": "contracts/BaseWasabiPool.sol:25"
          },
          {
            "label": "addressProvider",
            "offset": 1,
            "slot": "0",
            "type": "t_contract(IAddressProvider)14515",
            "contract": "BaseWasabiPool",
            "src": "contracts/BaseWasabiPool.sol:28"
          },
          {
            "label": "positions",
            "offset": 0,
            "slot": "1",
            "type": "t_mapping(t_uint256,t_bytes32)",
            "contract": "BaseWasabiPool",
            "src": "contracts/BaseWasabiPool.sol:31"
          },
          {
            "label": "vaults",
            "offset": 0,
            "slot": "2",
            "type": "t_mapping(t_address,t_address)",
            "contract": "BaseWasabiPool",
            "src": "contracts/BaseWasabiPool.sol:34"
          },
          {
            "label": "baseTokens",
            "offset": 0,
            "slot": "3",
            "type": "t_mapping(t_address,t_bool)",
            "contract": "BaseWasabiPool",
            "src": "contracts/BaseWasabiPool.sol:37"
          }
        ],
        "types": {
          "t_address": {
            "label": "address",
            "numberOfBytes": "20"
          },
          "t_bool": {
            "label": "bool",
            "numberOfBytes": "1"
          },
          "t_bytes32": {
            "label": "bytes32",
            "numberOfBytes": "32"
          },
          "t_string_storage": {
            "label": "string",
            "numberOfBytes": "32"
          },
          "t_struct(EIP712Storage)732_storage": {
            "label": "struct EIP712Upgradeable.EIP712Storage",
            "members": [
              {
                "label": "_hashedName",
                "type": "t_bytes32",
                "offset": 0,
                "slot": "0"
              },
              {
                "label": "_hashedVersion",
                "type": "t_bytes32",
                "offset": 0,
                "slot": "1"
              },
              {
                "label": "_name",
                "type": "t_string_storage",
                "offset": 0,
                "slot": "2"
              },
              {
                "label": "_version",
                "type": "t_string_storage",
                "offset": 0,
                "slot": "3"
              }
            ],
            "numberOfBytes": "128"
          },
          "t_struct(InitializableStorage)306_storage": {
            "label": "struct Initializable.InitializableStorage",
            "members": [
              {
                "label": "_initialized",
                "type": "t_uint64",
                "offset": 0,
                "slot": "0"
              },
              {
                "label": "_initializing",
                "type": "t_bool",
                "offset": 8,
                "slot": "0"
              }
            ],
            "numberOfBytes": "32"
          },
          "t_struct(OwnableStorage)14_storage": {
            "label": "struct OwnableUpgradeable.OwnableStorage",
            "members": [
              {
                "label": "_owner",
                "type": "t_address",
                "offset": 0,
                "slot": "0"
              }
            ],
            "numberOfBytes": "32"
          },
          "t_struct(ReentrancyGuardStorage)680_storage": {
            "label": "struct ReentrancyGuardUpgradeable.ReentrancyGuardStorage",
            "members": [
              {
                "label": "_status",
                "type": "t_uint256",
                "offset": 0,
                "slot": "0"
              }
            ],
            "numberOfBytes": "32"
          },
          "t_uint256": {
            "label": "uint256",
            "numberOfBytes": "32"
          },
          "t_uint64": {
            "label": "uint64",
            "numberOfBytes": "8"
          },
          "t_contract(IAddressProvider)14515": {
            "label": "contract IAddressProvider",
            "numberOfBytes": "20"
          },
          "t_mapping(t_address,t_address)": {
            "label": "mapping(address => address)",
            "numberOfBytes": "32"
          },
          "t_mapping(t_address,t_bool)": {
            "label": "mapping(address => bool)",
            "numberOfBytes": "32"
          },
          "t_mapping(t_uint256,t_bytes32)": {
            "label": "mapping(uint256 => bytes32)",
            "numberOfBytes": "32"
          }
        },
        "namespaces": {
          "erc7201:openzeppelin.storage.EIP712": [
            {
              "contract": "EIP712Upgradeable",
              "label": "_hashedName",
              "type": "t_bytes32",
              "src": "@openzeppelin/contracts-upgradeable/utils/cryptography/EIP712Upgradeable.sol:39",
              "offset": 0,
              "slot": "0"
            },
            {
              "contract": "EIP712Upgradeable",
              "label": "_hashedVersion",
              "type": "t_bytes32",
              "src": "@openzeppelin/contracts-upgradeable/utils/cryptography/EIP712Upgradeable.sol:41",
              "offset": 0,
              "slot": "1"
            },
            {
              "contract": "EIP712Upgradeable",
              "label": "_name",
              "type": "t_string_storage",
              "src": "@openzeppelin/contracts-upgradeable/utils/cryptography/EIP712Upgradeable.sol:43",
              "offset": 0,
              "slot": "2"
            },
            {
              "contract": "EIP712Upgradeable",
              "label": "_version",
              "type": "t_string_storage",
              "src": "@openzeppelin/contracts-upgradeable/utils/cryptography/EIP712Upgradeable.sol:44",
              "offset": 0,
              "slot": "3"
            }
          ],
          "erc7201:openzeppelin.storage.ReentrancyGuard": [
            {
              "contract": "ReentrancyGuardUpgradeable",
              "label": "_status",
              "type": "t_uint256",
              "src": "@openzeppelin/contracts-upgradeable/utils/ReentrancyGuardUpgradeable.sol:40",
              "offset": 0,
              "slot": "0"
            }
          ],
          "erc7201:openzeppelin.storage.Ownable": [
            {
              "contract": "OwnableUpgradeable",
              "label": "_owner",
              "type": "t_address",
              "src": "@openzeppelin/contracts-upgradeable/access/OwnableUpgradeable.sol:24",
              "offset": 0,
              "slot": "0"
            }
          ],
          "erc7201:openzeppelin.storage.Initializable": [
            {
              "contract": "Initializable",
              "label": "_initialized",
              "type": "t_uint64",
              "src": "@openzeppelin/contracts-upgradeable/proxy/utils/Initializable.sol:69",
              "offset": 0,
              "slot": "0"
            },
            {
              "contract": "Initializable",
              "label": "_initializing",
              "type": "t_bool",
              "src": "@openzeppelin/contracts-upgradeable/proxy/utils/Initializable.sol:73",
              "offset": 8,
              "slot": "0"
            }
          ]
        }
      }
    },
    "7ec32a0dbb84dabad9016cc1e60768ebc7222d7267e9d88ae3b12dba8295c7b1": {
      "address": "0x731CDb54D666F7B4039ba93E393D757A4d8C4006",
      "txHash": "0x7a80ff44a2042f4e53271526eb1ee1d14e3eb4871b1ff31ce92a40416cbb933c",
      "layout": {
        "solcVersion": "0.8.23",
        "storage": [
          {
            "label": "pool",
            "offset": 0,
            "slot": "0",
            "type": "t_contract(IWasabiPerps)12707",
            "contract": "WasabiVault",
            "src": "contracts/vaults/WasabiVault.sol:16"
          },
          {
            "label": "totalAssetValue",
            "offset": 0,
            "slot": "1",
            "type": "t_uint256",
            "contract": "WasabiVault",
            "src": "contracts/vaults/WasabiVault.sol:17"
          },
          {
            "label": "addressProvider",
            "offset": 0,
            "slot": "2",
            "type": "t_contract(IAddressProvider)14515",
            "contract": "WasabiVault",
            "src": "contracts/vaults/WasabiVault.sol:18"
          }
        ],
        "types": {
          "t_address": {
            "label": "address",
            "numberOfBytes": "20"
          },
          "t_bool": {
            "label": "bool",
            "numberOfBytes": "1"
          },
          "t_contract(IERC20)1319": {
            "label": "contract IERC20",
            "numberOfBytes": "20"
          },
          "t_mapping(t_address,t_mapping(t_address,t_uint256))": {
            "label": "mapping(address => mapping(address => uint256))",
            "numberOfBytes": "32"
          },
          "t_mapping(t_address,t_uint256)": {
            "label": "mapping(address => uint256)",
            "numberOfBytes": "32"
          },
          "t_string_storage": {
            "label": "string",
            "numberOfBytes": "32"
          },
          "t_struct(ERC20Storage)440_storage": {
            "label": "struct ERC20Upgradeable.ERC20Storage",
            "members": [
              {
                "label": "_balances",
                "type": "t_mapping(t_address,t_uint256)",
                "offset": 0,
                "slot": "0"
              },
              {
                "label": "_allowances",
                "type": "t_mapping(t_address,t_mapping(t_address,t_uint256))",
                "offset": 0,
                "slot": "1"
              },
              {
                "label": "_totalSupply",
                "type": "t_uint256",
                "offset": 0,
                "slot": "2"
              },
              {
                "label": "_name",
                "type": "t_string_storage",
                "offset": 0,
                "slot": "3"
              },
              {
                "label": "_symbol",
                "type": "t_string_storage",
                "offset": 0,
                "slot": "4"
              }
            ],
            "numberOfBytes": "160"
          },
          "t_struct(ERC4626Storage)533_storage": {
            "label": "struct ERC4626Upgradeable.ERC4626Storage",
            "members": [
              {
                "label": "_asset",
                "type": "t_contract(IERC20)1319",
                "offset": 0,
                "slot": "0"
              },
              {
                "label": "_underlyingDecimals",
                "type": "t_uint8",
                "offset": 20,
                "slot": "0"
              }
            ],
            "numberOfBytes": "32"
          },
          "t_struct(InitializableStorage)306_storage": {
            "label": "struct Initializable.InitializableStorage",
            "members": [
              {
                "label": "_initialized",
                "type": "t_uint64",
                "offset": 0,
                "slot": "0"
              },
              {
                "label": "_initializing",
                "type": "t_bool",
                "offset": 8,
                "slot": "0"
              }
            ],
            "numberOfBytes": "32"
          },
          "t_struct(OwnableStorage)14_storage": {
            "label": "struct OwnableUpgradeable.OwnableStorage",
            "members": [
              {
                "label": "_owner",
                "type": "t_address",
                "offset": 0,
                "slot": "0"
              }
            ],
            "numberOfBytes": "32"
          },
          "t_struct(ReentrancyGuardStorage)680_storage": {
            "label": "struct ReentrancyGuardUpgradeable.ReentrancyGuardStorage",
            "members": [
              {
                "label": "_status",
                "type": "t_uint256",
                "offset": 0,
                "slot": "0"
              }
            ],
            "numberOfBytes": "32"
          },
          "t_uint256": {
            "label": "uint256",
            "numberOfBytes": "32"
          },
          "t_uint64": {
            "label": "uint64",
            "numberOfBytes": "8"
          },
          "t_uint8": {
            "label": "uint8",
            "numberOfBytes": "1"
          },
          "t_contract(IAddressProvider)14515": {
            "label": "contract IAddressProvider",
            "numberOfBytes": "20"
          },
          "t_contract(IWasabiPerps)12707": {
            "label": "contract IWasabiPerps",
            "numberOfBytes": "20"
          }
        },
        "namespaces": {
          "erc7201:openzeppelin.storage.ReentrancyGuard": [
            {
              "contract": "ReentrancyGuardUpgradeable",
              "label": "_status",
              "type": "t_uint256",
              "src": "@openzeppelin/contracts-upgradeable/utils/ReentrancyGuardUpgradeable.sol:40",
              "offset": 0,
              "slot": "0"
            }
          ],
          "erc7201:openzeppelin.storage.ERC4626": [
            {
              "contract": "ERC4626Upgradeable",
              "label": "_asset",
              "type": "t_contract(IERC20)1319",
              "src": "@openzeppelin/contracts-upgradeable/token/ERC20/extensions/ERC4626Upgradeable.sol:56",
              "offset": 0,
              "slot": "0"
            },
            {
              "contract": "ERC4626Upgradeable",
              "label": "_underlyingDecimals",
              "type": "t_uint8",
              "src": "@openzeppelin/contracts-upgradeable/token/ERC20/extensions/ERC4626Upgradeable.sol:57",
              "offset": 20,
              "slot": "0"
            }
          ],
          "erc7201:openzeppelin.storage.Ownable": [
            {
              "contract": "OwnableUpgradeable",
              "label": "_owner",
              "type": "t_address",
              "src": "@openzeppelin/contracts-upgradeable/access/OwnableUpgradeable.sol:24",
              "offset": 0,
              "slot": "0"
            }
          ],
          "erc7201:openzeppelin.storage.ERC20": [
            {
              "contract": "ERC20Upgradeable",
              "label": "_balances",
              "type": "t_mapping(t_address,t_uint256)",
              "src": "@openzeppelin/contracts-upgradeable/token/ERC20/ERC20Upgradeable.sol:38",
              "offset": 0,
              "slot": "0"
            },
            {
              "contract": "ERC20Upgradeable",
              "label": "_allowances",
              "type": "t_mapping(t_address,t_mapping(t_address,t_uint256))",
              "src": "@openzeppelin/contracts-upgradeable/token/ERC20/ERC20Upgradeable.sol:40",
              "offset": 0,
              "slot": "1"
            },
            {
              "contract": "ERC20Upgradeable",
              "label": "_totalSupply",
              "type": "t_uint256",
              "src": "@openzeppelin/contracts-upgradeable/token/ERC20/ERC20Upgradeable.sol:42",
              "offset": 0,
              "slot": "2"
            },
            {
              "contract": "ERC20Upgradeable",
              "label": "_name",
              "type": "t_string_storage",
              "src": "@openzeppelin/contracts-upgradeable/token/ERC20/ERC20Upgradeable.sol:44",
              "offset": 0,
              "slot": "3"
            },
            {
              "contract": "ERC20Upgradeable",
              "label": "_symbol",
              "type": "t_string_storage",
              "src": "@openzeppelin/contracts-upgradeable/token/ERC20/ERC20Upgradeable.sol:45",
              "offset": 0,
              "slot": "4"
            }
          ],
          "erc7201:openzeppelin.storage.Initializable": [
            {
              "contract": "Initializable",
              "label": "_initialized",
              "type": "t_uint64",
              "src": "@openzeppelin/contracts-upgradeable/proxy/utils/Initializable.sol:69",
              "offset": 0,
              "slot": "0"
            },
            {
              "contract": "Initializable",
              "label": "_initializing",
              "type": "t_bool",
              "src": "@openzeppelin/contracts-upgradeable/proxy/utils/Initializable.sol:73",
              "offset": 8,
              "slot": "0"
            }
          ]
        }
      }
    },
    "38c1fb7f15f81be3bbabdc3f0d37ee0eb5d4305703282f56498c4ceed5dac403": {
      "address": "0x36a2412AeA14051d2ac31A15918F1677762Cd5ee",
      "txHash": "0xe2825ec4ad7b16ea636e6bb434ab1ec4370e033ee8648578a45a4ed79bf8b223",
      "layout": {
        "solcVersion": "0.8.23",
        "storage": [
          {
            "label": "isLongPool",
            "offset": 0,
            "slot": "0",
            "type": "t_bool",
            "contract": "BaseWasabiPool",
            "src": "contracts/BaseWasabiPool.sol:25"
          },
          {
            "label": "addressProvider",
            "offset": 1,
            "slot": "0",
            "type": "t_contract(IAddressProvider)11747",
            "contract": "BaseWasabiPool",
            "src": "contracts/BaseWasabiPool.sol:28"
          },
          {
            "label": "positions",
            "offset": 0,
            "slot": "1",
            "type": "t_mapping(t_uint256,t_bytes32)",
            "contract": "BaseWasabiPool",
            "src": "contracts/BaseWasabiPool.sol:31"
          },
          {
            "label": "vaults",
            "offset": 0,
            "slot": "2",
            "type": "t_mapping(t_address,t_address)",
            "contract": "BaseWasabiPool",
            "src": "contracts/BaseWasabiPool.sol:34"
          },
          {
            "label": "baseTokens",
            "offset": 0,
            "slot": "3",
            "type": "t_mapping(t_address,t_bool)",
            "contract": "BaseWasabiPool",
            "src": "contracts/BaseWasabiPool.sol:37"
          }
        ],
        "types": {
          "t_address": {
            "label": "address",
            "numberOfBytes": "20"
          },
          "t_bool": {
            "label": "bool",
            "numberOfBytes": "1"
          },
          "t_bytes32": {
            "label": "bytes32",
            "numberOfBytes": "32"
          },
          "t_string_storage": {
            "label": "string",
            "numberOfBytes": "32"
          },
          "t_struct(EIP712Storage)505_storage": {
            "label": "struct EIP712Upgradeable.EIP712Storage",
            "members": [
              {
                "label": "_hashedName",
                "type": "t_bytes32",
                "offset": 0,
                "slot": "0"
              },
              {
                "label": "_hashedVersion",
                "type": "t_bytes32",
                "offset": 0,
                "slot": "1"
              },
              {
                "label": "_name",
                "type": "t_string_storage",
                "offset": 0,
                "slot": "2"
              },
              {
                "label": "_version",
                "type": "t_string_storage",
                "offset": 0,
                "slot": "3"
              }
            ],
            "numberOfBytes": "128"
          },
          "t_struct(InitializableStorage)306_storage": {
            "label": "struct Initializable.InitializableStorage",
            "members": [
              {
                "label": "_initialized",
                "type": "t_uint64",
                "offset": 0,
                "slot": "0"
              },
              {
                "label": "_initializing",
                "type": "t_bool",
                "offset": 8,
                "slot": "0"
              }
            ],
            "numberOfBytes": "32"
          },
          "t_struct(OwnableStorage)14_storage": {
            "label": "struct OwnableUpgradeable.OwnableStorage",
            "members": [
              {
                "label": "_owner",
                "type": "t_address",
                "offset": 0,
                "slot": "0"
              }
            ],
            "numberOfBytes": "32"
          },
          "t_struct(ReentrancyGuardStorage)453_storage": {
            "label": "struct ReentrancyGuardUpgradeable.ReentrancyGuardStorage",
            "members": [
              {
                "label": "_status",
                "type": "t_uint256",
                "offset": 0,
                "slot": "0"
              }
            ],
            "numberOfBytes": "32"
          },
          "t_uint256": {
            "label": "uint256",
            "numberOfBytes": "32"
          },
          "t_uint64": {
            "label": "uint64",
            "numberOfBytes": "8"
          },
          "t_contract(IAddressProvider)11747": {
            "label": "contract IAddressProvider",
            "numberOfBytes": "20"
          },
          "t_mapping(t_address,t_address)": {
            "label": "mapping(address => address)",
            "numberOfBytes": "32"
          },
          "t_mapping(t_address,t_bool)": {
            "label": "mapping(address => bool)",
            "numberOfBytes": "32"
          },
          "t_mapping(t_uint256,t_bytes32)": {
            "label": "mapping(uint256 => bytes32)",
            "numberOfBytes": "32"
          }
        },
        "namespaces": {
          "erc7201:openzeppelin.storage.EIP712": [
            {
              "contract": "EIP712Upgradeable",
              "label": "_hashedName",
              "type": "t_bytes32",
              "src": "@openzeppelin/contracts-upgradeable/utils/cryptography/EIP712Upgradeable.sol:39",
              "offset": 0,
              "slot": "0"
            },
            {
              "contract": "EIP712Upgradeable",
              "label": "_hashedVersion",
              "type": "t_bytes32",
              "src": "@openzeppelin/contracts-upgradeable/utils/cryptography/EIP712Upgradeable.sol:41",
              "offset": 0,
              "slot": "1"
            },
            {
              "contract": "EIP712Upgradeable",
              "label": "_name",
              "type": "t_string_storage",
              "src": "@openzeppelin/contracts-upgradeable/utils/cryptography/EIP712Upgradeable.sol:43",
              "offset": 0,
              "slot": "2"
            },
            {
              "contract": "EIP712Upgradeable",
              "label": "_version",
              "type": "t_string_storage",
              "src": "@openzeppelin/contracts-upgradeable/utils/cryptography/EIP712Upgradeable.sol:44",
              "offset": 0,
              "slot": "3"
            }
          ],
          "erc7201:openzeppelin.storage.ReentrancyGuard": [
            {
              "contract": "ReentrancyGuardUpgradeable",
              "label": "_status",
              "type": "t_uint256",
              "src": "@openzeppelin/contracts-upgradeable/utils/ReentrancyGuardUpgradeable.sol:40",
              "offset": 0,
              "slot": "0"
            }
          ],
          "erc7201:openzeppelin.storage.Ownable": [
            {
              "contract": "OwnableUpgradeable",
              "label": "_owner",
              "type": "t_address",
              "src": "@openzeppelin/contracts-upgradeable/access/OwnableUpgradeable.sol:24",
              "offset": 0,
              "slot": "0"
            }
          ],
          "erc7201:openzeppelin.storage.Initializable": [
            {
              "contract": "Initializable",
              "label": "_initialized",
              "type": "t_uint64",
              "src": "@openzeppelin/contracts-upgradeable/proxy/utils/Initializable.sol:69",
              "offset": 0,
              "slot": "0"
            },
            {
              "contract": "Initializable",
              "label": "_initializing",
              "type": "t_bool",
              "src": "@openzeppelin/contracts-upgradeable/proxy/utils/Initializable.sol:73",
              "offset": 8,
              "slot": "0"
            }
          ]
        }
      }
    },
    "9e9b534c041e45cf00afffd9e3e66be03d2f6271189938aaf4744a19e13ac405": {
      "address": "0x67aa71e21Aa407B8b260802c744ef63Dc37860Ba",
      "txHash": "0xeceab8365d5109e00360af6edbbb4e5eda7cb4dc8f2d6b801099174ed55ba954",
      "layout": {
        "solcVersion": "0.8.23",
        "storage": [
          {
            "label": "isLongPool",
            "offset": 0,
            "slot": "0",
            "type": "t_bool",
            "contract": "BaseWasabiPool",
            "src": "contracts/BaseWasabiPool.sol:25"
          },
          {
            "label": "addressProvider",
            "offset": 1,
            "slot": "0",
            "type": "t_contract(IAddressProvider)11030",
            "contract": "BaseWasabiPool",
            "src": "contracts/BaseWasabiPool.sol:28"
          },
          {
            "label": "positions",
            "offset": 0,
            "slot": "1",
            "type": "t_mapping(t_uint256,t_bytes32)",
            "contract": "BaseWasabiPool",
            "src": "contracts/BaseWasabiPool.sol:31"
          },
          {
            "label": "vaults",
            "offset": 0,
            "slot": "2",
            "type": "t_mapping(t_address,t_address)",
            "contract": "BaseWasabiPool",
            "src": "contracts/BaseWasabiPool.sol:34"
          },
          {
            "label": "baseTokens",
            "offset": 0,
            "slot": "3",
            "type": "t_mapping(t_address,t_bool)",
            "contract": "BaseWasabiPool",
            "src": "contracts/BaseWasabiPool.sol:37"
          }
        ],
        "types": {
          "t_address": {
            "label": "address",
            "numberOfBytes": "20"
          },
          "t_bool": {
            "label": "bool",
            "numberOfBytes": "1"
          },
          "t_bytes32": {
            "label": "bytes32",
            "numberOfBytes": "32"
          },
          "t_string_storage": {
            "label": "string",
            "numberOfBytes": "32"
          },
          "t_struct(EIP712Storage)505_storage": {
            "label": "struct EIP712Upgradeable.EIP712Storage",
            "members": [
              {
                "label": "_hashedName",
                "type": "t_bytes32",
                "offset": 0,
                "slot": "0"
              },
              {
                "label": "_hashedVersion",
                "type": "t_bytes32",
                "offset": 0,
                "slot": "1"
              },
              {
                "label": "_name",
                "type": "t_string_storage",
                "offset": 0,
                "slot": "2"
              },
              {
                "label": "_version",
                "type": "t_string_storage",
                "offset": 0,
                "slot": "3"
              }
            ],
            "numberOfBytes": "128"
          },
          "t_struct(InitializableStorage)306_storage": {
            "label": "struct Initializable.InitializableStorage",
            "members": [
              {
                "label": "_initialized",
                "type": "t_uint64",
                "offset": 0,
                "slot": "0"
              },
              {
                "label": "_initializing",
                "type": "t_bool",
                "offset": 8,
                "slot": "0"
              }
            ],
            "numberOfBytes": "32"
          },
          "t_struct(OwnableStorage)14_storage": {
            "label": "struct OwnableUpgradeable.OwnableStorage",
            "members": [
              {
                "label": "_owner",
                "type": "t_address",
                "offset": 0,
                "slot": "0"
              }
            ],
            "numberOfBytes": "32"
          },
          "t_struct(ReentrancyGuardStorage)453_storage": {
            "label": "struct ReentrancyGuardUpgradeable.ReentrancyGuardStorage",
            "members": [
              {
                "label": "_status",
                "type": "t_uint256",
                "offset": 0,
                "slot": "0"
              }
            ],
            "numberOfBytes": "32"
          },
          "t_uint256": {
            "label": "uint256",
            "numberOfBytes": "32"
          },
          "t_uint64": {
            "label": "uint64",
            "numberOfBytes": "8"
          },
          "t_contract(IAddressProvider)11030": {
            "label": "contract IAddressProvider",
            "numberOfBytes": "20"
          },
          "t_mapping(t_address,t_address)": {
            "label": "mapping(address => address)",
            "numberOfBytes": "32"
          },
          "t_mapping(t_address,t_bool)": {
            "label": "mapping(address => bool)",
            "numberOfBytes": "32"
          },
          "t_mapping(t_uint256,t_bytes32)": {
            "label": "mapping(uint256 => bytes32)",
            "numberOfBytes": "32"
          }
        },
        "namespaces": {
          "erc7201:openzeppelin.storage.EIP712": [
            {
              "contract": "EIP712Upgradeable",
              "label": "_hashedName",
              "type": "t_bytes32",
              "src": "@openzeppelin/contracts-upgradeable/utils/cryptography/EIP712Upgradeable.sol:39",
              "offset": 0,
              "slot": "0"
            },
            {
              "contract": "EIP712Upgradeable",
              "label": "_hashedVersion",
              "type": "t_bytes32",
              "src": "@openzeppelin/contracts-upgradeable/utils/cryptography/EIP712Upgradeable.sol:41",
              "offset": 0,
              "slot": "1"
            },
            {
              "contract": "EIP712Upgradeable",
              "label": "_name",
              "type": "t_string_storage",
              "src": "@openzeppelin/contracts-upgradeable/utils/cryptography/EIP712Upgradeable.sol:43",
              "offset": 0,
              "slot": "2"
            },
            {
              "contract": "EIP712Upgradeable",
              "label": "_version",
              "type": "t_string_storage",
              "src": "@openzeppelin/contracts-upgradeable/utils/cryptography/EIP712Upgradeable.sol:44",
              "offset": 0,
              "slot": "3"
            }
          ],
          "erc7201:openzeppelin.storage.ReentrancyGuard": [
            {
              "contract": "ReentrancyGuardUpgradeable",
              "label": "_status",
              "type": "t_uint256",
              "src": "@openzeppelin/contracts-upgradeable/utils/ReentrancyGuardUpgradeable.sol:40",
              "offset": 0,
              "slot": "0"
            }
          ],
          "erc7201:openzeppelin.storage.Ownable": [
            {
              "contract": "OwnableUpgradeable",
              "label": "_owner",
              "type": "t_address",
              "src": "@openzeppelin/contracts-upgradeable/access/OwnableUpgradeable.sol:24",
              "offset": 0,
              "slot": "0"
            }
          ],
          "erc7201:openzeppelin.storage.Initializable": [
            {
              "contract": "Initializable",
              "label": "_initialized",
              "type": "t_uint64",
              "src": "@openzeppelin/contracts-upgradeable/proxy/utils/Initializable.sol:69",
              "offset": 0,
              "slot": "0"
            },
            {
              "contract": "Initializable",
              "label": "_initializing",
              "type": "t_bool",
              "src": "@openzeppelin/contracts-upgradeable/proxy/utils/Initializable.sol:73",
              "offset": 8,
              "slot": "0"
            }
          ]
        }
      },
      "allAddresses": [
        "0x67aa71e21Aa407B8b260802c744ef63Dc37860Ba",
        "0x188DD543541BBEAa2D6A51b10E5f1Fd3b00F3B83",
        "0xBa2117d32fd632a510333E43f407B7F4F6e022ed",
        "0xe5a8058587e45B12eA0F26Bb955A8a33C7E488B6"
      ]
    },
    "8f98412f5c7639b7aeb69723bf706102aa6903112ff7c7253f77ad4786939af0": {
      "address": "0x4b2182d34dD15d2BA4ED5A4a876737BAfb7c918d",
      "txHash": "0x11f695db581a31bb7be7d83032f6121a9a63c0b80fc2c640a5417c3796a9c8df",
      "layout": {
        "solcVersion": "0.8.23",
        "storage": [
          {
            "label": "isLongPool",
            "offset": 0,
            "slot": "0",
            "type": "t_bool",
            "contract": "BaseWasabiPool",
            "src": "contracts/BaseWasabiPool.sol:25"
          },
          {
            "label": "addressProvider",
            "offset": 1,
            "slot": "0",
            "type": "t_contract(IAddressProvider)11030",
            "contract": "BaseWasabiPool",
            "src": "contracts/BaseWasabiPool.sol:28"
          },
          {
            "label": "positions",
            "offset": 0,
            "slot": "1",
            "type": "t_mapping(t_uint256,t_bytes32)",
            "contract": "BaseWasabiPool",
            "src": "contracts/BaseWasabiPool.sol:31"
          },
          {
            "label": "vaults",
            "offset": 0,
            "slot": "2",
            "type": "t_mapping(t_address,t_address)",
            "contract": "BaseWasabiPool",
            "src": "contracts/BaseWasabiPool.sol:34"
          },
          {
            "label": "baseTokens",
            "offset": 0,
            "slot": "3",
            "type": "t_mapping(t_address,t_bool)",
            "contract": "BaseWasabiPool",
            "src": "contracts/BaseWasabiPool.sol:37"
          }
        ],
        "types": {
          "t_address": {
            "label": "address",
            "numberOfBytes": "20"
          },
          "t_bool": {
            "label": "bool",
            "numberOfBytes": "1"
          },
          "t_bytes32": {
            "label": "bytes32",
            "numberOfBytes": "32"
          },
          "t_string_storage": {
            "label": "string",
            "numberOfBytes": "32"
          },
          "t_struct(EIP712Storage)505_storage": {
            "label": "struct EIP712Upgradeable.EIP712Storage",
            "members": [
              {
                "label": "_hashedName",
                "type": "t_bytes32",
                "offset": 0,
                "slot": "0"
              },
              {
                "label": "_hashedVersion",
                "type": "t_bytes32",
                "offset": 0,
                "slot": "1"
              },
              {
                "label": "_name",
                "type": "t_string_storage",
                "offset": 0,
                "slot": "2"
              },
              {
                "label": "_version",
                "type": "t_string_storage",
                "offset": 0,
                "slot": "3"
              }
            ],
            "numberOfBytes": "128"
          },
          "t_struct(InitializableStorage)306_storage": {
            "label": "struct Initializable.InitializableStorage",
            "members": [
              {
                "label": "_initialized",
                "type": "t_uint64",
                "offset": 0,
                "slot": "0"
              },
              {
                "label": "_initializing",
                "type": "t_bool",
                "offset": 8,
                "slot": "0"
              }
            ],
            "numberOfBytes": "32"
          },
          "t_struct(OwnableStorage)14_storage": {
            "label": "struct OwnableUpgradeable.OwnableStorage",
            "members": [
              {
                "label": "_owner",
                "type": "t_address",
                "offset": 0,
                "slot": "0"
              }
            ],
            "numberOfBytes": "32"
          },
          "t_struct(ReentrancyGuardStorage)453_storage": {
            "label": "struct ReentrancyGuardUpgradeable.ReentrancyGuardStorage",
            "members": [
              {
                "label": "_status",
                "type": "t_uint256",
                "offset": 0,
                "slot": "0"
              }
            ],
            "numberOfBytes": "32"
          },
          "t_uint256": {
            "label": "uint256",
            "numberOfBytes": "32"
          },
          "t_uint64": {
            "label": "uint64",
            "numberOfBytes": "8"
          },
          "t_contract(IAddressProvider)11030": {
            "label": "contract IAddressProvider",
            "numberOfBytes": "20"
          },
          "t_mapping(t_address,t_address)": {
            "label": "mapping(address => address)",
            "numberOfBytes": "32"
          },
          "t_mapping(t_address,t_bool)": {
            "label": "mapping(address => bool)",
            "numberOfBytes": "32"
          },
          "t_mapping(t_uint256,t_bytes32)": {
            "label": "mapping(uint256 => bytes32)",
            "numberOfBytes": "32"
          }
        },
        "namespaces": {
          "erc7201:openzeppelin.storage.EIP712": [
            {
              "contract": "EIP712Upgradeable",
              "label": "_hashedName",
              "type": "t_bytes32",
              "src": "@openzeppelin/contracts-upgradeable/utils/cryptography/EIP712Upgradeable.sol:39",
              "offset": 0,
              "slot": "0"
            },
            {
              "contract": "EIP712Upgradeable",
              "label": "_hashedVersion",
              "type": "t_bytes32",
              "src": "@openzeppelin/contracts-upgradeable/utils/cryptography/EIP712Upgradeable.sol:41",
              "offset": 0,
              "slot": "1"
            },
            {
              "contract": "EIP712Upgradeable",
              "label": "_name",
              "type": "t_string_storage",
              "src": "@openzeppelin/contracts-upgradeable/utils/cryptography/EIP712Upgradeable.sol:43",
              "offset": 0,
              "slot": "2"
            },
            {
              "contract": "EIP712Upgradeable",
              "label": "_version",
              "type": "t_string_storage",
              "src": "@openzeppelin/contracts-upgradeable/utils/cryptography/EIP712Upgradeable.sol:44",
              "offset": 0,
              "slot": "3"
            }
          ],
          "erc7201:openzeppelin.storage.ReentrancyGuard": [
            {
              "contract": "ReentrancyGuardUpgradeable",
              "label": "_status",
              "type": "t_uint256",
              "src": "@openzeppelin/contracts-upgradeable/utils/ReentrancyGuardUpgradeable.sol:40",
              "offset": 0,
              "slot": "0"
            }
          ],
          "erc7201:openzeppelin.storage.Ownable": [
            {
              "contract": "OwnableUpgradeable",
              "label": "_owner",
              "type": "t_address",
              "src": "@openzeppelin/contracts-upgradeable/access/OwnableUpgradeable.sol:24",
              "offset": 0,
              "slot": "0"
            }
          ],
          "erc7201:openzeppelin.storage.Initializable": [
            {
              "contract": "Initializable",
              "label": "_initialized",
              "type": "t_uint64",
              "src": "@openzeppelin/contracts-upgradeable/proxy/utils/Initializable.sol:69",
              "offset": 0,
              "slot": "0"
            },
            {
              "contract": "Initializable",
              "label": "_initializing",
              "type": "t_bool",
              "src": "@openzeppelin/contracts-upgradeable/proxy/utils/Initializable.sol:73",
              "offset": 8,
              "slot": "0"
            }
          ]
        }
      }
    },
    "293599e1b5fbd4e5fd9435fdc398f726789833d8ecb0341fa9408033b71cb69d": {
      "address": "0x684331079Fde30fe842C8EfFdf98dFa2064c3438",
      "txHash": "0x66fd4fad6c447ffd1a3933d1fdeb275e909f5537492ab7b201ebabf86027d484",
      "layout": {
        "solcVersion": "0.8.23",
        "storage": [
          {
            "label": "isLongPool",
            "offset": 0,
            "slot": "0",
            "type": "t_bool",
            "contract": "BaseWasabiPool",
            "src": "contracts/BaseWasabiPool.sol:25"
          },
          {
            "label": "addressProvider",
            "offset": 1,
            "slot": "0",
            "type": "t_contract(IAddressProvider)11747",
            "contract": "BaseWasabiPool",
            "src": "contracts/BaseWasabiPool.sol:28"
          },
          {
            "label": "positions",
            "offset": 0,
            "slot": "1",
            "type": "t_mapping(t_uint256,t_bytes32)",
            "contract": "BaseWasabiPool",
            "src": "contracts/BaseWasabiPool.sol:31"
          },
          {
            "label": "vaults",
            "offset": 0,
            "slot": "2",
            "type": "t_mapping(t_address,t_address)",
            "contract": "BaseWasabiPool",
            "src": "contracts/BaseWasabiPool.sol:34"
          },
          {
            "label": "baseTokens",
            "offset": 0,
            "slot": "3",
            "type": "t_mapping(t_address,t_bool)",
            "contract": "BaseWasabiPool",
            "src": "contracts/BaseWasabiPool.sol:37"
          }
        ],
        "types": {
          "t_address": {
            "label": "address",
            "numberOfBytes": "20"
          },
          "t_bool": {
            "label": "bool",
            "numberOfBytes": "1"
          },
          "t_bytes32": {
            "label": "bytes32",
            "numberOfBytes": "32"
          },
          "t_string_storage": {
            "label": "string",
            "numberOfBytes": "32"
          },
          "t_struct(EIP712Storage)505_storage": {
            "label": "struct EIP712Upgradeable.EIP712Storage",
            "members": [
              {
                "label": "_hashedName",
                "type": "t_bytes32",
                "offset": 0,
                "slot": "0"
              },
              {
                "label": "_hashedVersion",
                "type": "t_bytes32",
                "offset": 0,
                "slot": "1"
              },
              {
                "label": "_name",
                "type": "t_string_storage",
                "offset": 0,
                "slot": "2"
              },
              {
                "label": "_version",
                "type": "t_string_storage",
                "offset": 0,
                "slot": "3"
              }
            ],
            "numberOfBytes": "128"
          },
          "t_struct(InitializableStorage)306_storage": {
            "label": "struct Initializable.InitializableStorage",
            "members": [
              {
                "label": "_initialized",
                "type": "t_uint64",
                "offset": 0,
                "slot": "0"
              },
              {
                "label": "_initializing",
                "type": "t_bool",
                "offset": 8,
                "slot": "0"
              }
            ],
            "numberOfBytes": "32"
          },
          "t_struct(OwnableStorage)14_storage": {
            "label": "struct OwnableUpgradeable.OwnableStorage",
            "members": [
              {
                "label": "_owner",
                "type": "t_address",
                "offset": 0,
                "slot": "0"
              }
            ],
            "numberOfBytes": "32"
          },
          "t_struct(ReentrancyGuardStorage)453_storage": {
            "label": "struct ReentrancyGuardUpgradeable.ReentrancyGuardStorage",
            "members": [
              {
                "label": "_status",
                "type": "t_uint256",
                "offset": 0,
                "slot": "0"
              }
            ],
            "numberOfBytes": "32"
          },
          "t_uint256": {
            "label": "uint256",
            "numberOfBytes": "32"
          },
          "t_uint64": {
            "label": "uint64",
            "numberOfBytes": "8"
          },
          "t_contract(IAddressProvider)11747": {
            "label": "contract IAddressProvider",
            "numberOfBytes": "20"
          },
          "t_mapping(t_address,t_address)": {
            "label": "mapping(address => address)",
            "numberOfBytes": "32"
          },
          "t_mapping(t_address,t_bool)": {
            "label": "mapping(address => bool)",
            "numberOfBytes": "32"
          },
          "t_mapping(t_uint256,t_bytes32)": {
            "label": "mapping(uint256 => bytes32)",
            "numberOfBytes": "32"
          }
        },
        "namespaces": {
          "erc7201:openzeppelin.storage.EIP712": [
            {
              "contract": "EIP712Upgradeable",
              "label": "_hashedName",
              "type": "t_bytes32",
              "src": "@openzeppelin/contracts-upgradeable/utils/cryptography/EIP712Upgradeable.sol:39",
              "offset": 0,
              "slot": "0"
            },
            {
              "contract": "EIP712Upgradeable",
              "label": "_hashedVersion",
              "type": "t_bytes32",
              "src": "@openzeppelin/contracts-upgradeable/utils/cryptography/EIP712Upgradeable.sol:41",
              "offset": 0,
              "slot": "1"
            },
            {
              "contract": "EIP712Upgradeable",
              "label": "_name",
              "type": "t_string_storage",
              "src": "@openzeppelin/contracts-upgradeable/utils/cryptography/EIP712Upgradeable.sol:43",
              "offset": 0,
              "slot": "2"
            },
            {
              "contract": "EIP712Upgradeable",
              "label": "_version",
              "type": "t_string_storage",
              "src": "@openzeppelin/contracts-upgradeable/utils/cryptography/EIP712Upgradeable.sol:44",
              "offset": 0,
              "slot": "3"
            }
          ],
          "erc7201:openzeppelin.storage.ReentrancyGuard": [
            {
              "contract": "ReentrancyGuardUpgradeable",
              "label": "_status",
              "type": "t_uint256",
              "src": "@openzeppelin/contracts-upgradeable/utils/ReentrancyGuardUpgradeable.sol:40",
              "offset": 0,
              "slot": "0"
            }
          ],
          "erc7201:openzeppelin.storage.Ownable": [
            {
              "contract": "OwnableUpgradeable",
              "label": "_owner",
              "type": "t_address",
              "src": "@openzeppelin/contracts-upgradeable/access/OwnableUpgradeable.sol:24",
              "offset": 0,
              "slot": "0"
            }
          ],
          "erc7201:openzeppelin.storage.Initializable": [
            {
              "contract": "Initializable",
              "label": "_initialized",
              "type": "t_uint64",
              "src": "@openzeppelin/contracts-upgradeable/proxy/utils/Initializable.sol:69",
              "offset": 0,
              "slot": "0"
            },
            {
              "contract": "Initializable",
              "label": "_initializing",
              "type": "t_bool",
              "src": "@openzeppelin/contracts-upgradeable/proxy/utils/Initializable.sol:73",
              "offset": 8,
              "slot": "0"
            }
          ]
        }
      }
    },
    "819968aec7e7743131d17712a921970f3521e026d48b7b9a4c6a6e78045414dc": {
      "address": "0x66a4dc9a441A124b959849274Ca9D6a3F5f38a23",
      "txHash": "0xc8522c0e0bc658a36731688b8eef8c27b87ff24e1a6028f75610ba9ab22bfe05",
      "layout": {
        "solcVersion": "0.8.23",
        "storage": [
          {
            "label": "isLongPool",
            "offset": 0,
            "slot": "0",
            "type": "t_bool",
            "contract": "BaseWasabiPool",
            "src": "contracts/BaseWasabiPool.sol:25"
          },
          {
            "label": "addressProvider",
            "offset": 1,
            "slot": "0",
            "type": "t_contract(IAddressProvider)11747",
            "contract": "BaseWasabiPool",
            "src": "contracts/BaseWasabiPool.sol:28"
          },
          {
            "label": "positions",
            "offset": 0,
            "slot": "1",
            "type": "t_mapping(t_uint256,t_bytes32)",
            "contract": "BaseWasabiPool",
            "src": "contracts/BaseWasabiPool.sol:31"
          },
          {
            "label": "vaults",
            "offset": 0,
            "slot": "2",
            "type": "t_mapping(t_address,t_address)",
            "contract": "BaseWasabiPool",
            "src": "contracts/BaseWasabiPool.sol:34"
          },
          {
            "label": "baseTokens",
            "offset": 0,
            "slot": "3",
            "type": "t_mapping(t_address,t_bool)",
            "contract": "BaseWasabiPool",
            "src": "contracts/BaseWasabiPool.sol:37"
          }
        ],
        "types": {
          "t_address": {
            "label": "address",
            "numberOfBytes": "20"
          },
          "t_bool": {
            "label": "bool",
            "numberOfBytes": "1"
          },
          "t_bytes32": {
            "label": "bytes32",
            "numberOfBytes": "32"
          },
          "t_string_storage": {
            "label": "string",
            "numberOfBytes": "32"
          },
          "t_struct(EIP712Storage)505_storage": {
            "label": "struct EIP712Upgradeable.EIP712Storage",
            "members": [
              {
                "label": "_hashedName",
                "type": "t_bytes32",
                "offset": 0,
                "slot": "0"
              },
              {
                "label": "_hashedVersion",
                "type": "t_bytes32",
                "offset": 0,
                "slot": "1"
              },
              {
                "label": "_name",
                "type": "t_string_storage",
                "offset": 0,
                "slot": "2"
              },
              {
                "label": "_version",
                "type": "t_string_storage",
                "offset": 0,
                "slot": "3"
              }
            ],
            "numberOfBytes": "128"
          },
          "t_struct(InitializableStorage)306_storage": {
            "label": "struct Initializable.InitializableStorage",
            "members": [
              {
                "label": "_initialized",
                "type": "t_uint64",
                "offset": 0,
                "slot": "0"
              },
              {
                "label": "_initializing",
                "type": "t_bool",
                "offset": 8,
                "slot": "0"
              }
            ],
            "numberOfBytes": "32"
          },
          "t_struct(OwnableStorage)14_storage": {
            "label": "struct OwnableUpgradeable.OwnableStorage",
            "members": [
              {
                "label": "_owner",
                "type": "t_address",
                "offset": 0,
                "slot": "0"
              }
            ],
            "numberOfBytes": "32"
          },
          "t_struct(ReentrancyGuardStorage)453_storage": {
            "label": "struct ReentrancyGuardUpgradeable.ReentrancyGuardStorage",
            "members": [
              {
                "label": "_status",
                "type": "t_uint256",
                "offset": 0,
                "slot": "0"
              }
            ],
            "numberOfBytes": "32"
          },
          "t_uint256": {
            "label": "uint256",
            "numberOfBytes": "32"
          },
          "t_uint64": {
            "label": "uint64",
            "numberOfBytes": "8"
          },
          "t_contract(IAddressProvider)11747": {
            "label": "contract IAddressProvider",
            "numberOfBytes": "20"
          },
          "t_mapping(t_address,t_address)": {
            "label": "mapping(address => address)",
            "numberOfBytes": "32"
          },
          "t_mapping(t_address,t_bool)": {
            "label": "mapping(address => bool)",
            "numberOfBytes": "32"
          },
          "t_mapping(t_uint256,t_bytes32)": {
            "label": "mapping(uint256 => bytes32)",
            "numberOfBytes": "32"
          }
        },
        "namespaces": {
          "erc7201:openzeppelin.storage.EIP712": [
            {
              "contract": "EIP712Upgradeable",
              "label": "_hashedName",
              "type": "t_bytes32",
              "src": "@openzeppelin/contracts-upgradeable/utils/cryptography/EIP712Upgradeable.sol:39",
              "offset": 0,
              "slot": "0"
            },
            {
              "contract": "EIP712Upgradeable",
              "label": "_hashedVersion",
              "type": "t_bytes32",
              "src": "@openzeppelin/contracts-upgradeable/utils/cryptography/EIP712Upgradeable.sol:41",
              "offset": 0,
              "slot": "1"
            },
            {
              "contract": "EIP712Upgradeable",
              "label": "_name",
              "type": "t_string_storage",
              "src": "@openzeppelin/contracts-upgradeable/utils/cryptography/EIP712Upgradeable.sol:43",
              "offset": 0,
              "slot": "2"
            },
            {
              "contract": "EIP712Upgradeable",
              "label": "_version",
              "type": "t_string_storage",
              "src": "@openzeppelin/contracts-upgradeable/utils/cryptography/EIP712Upgradeable.sol:44",
              "offset": 0,
              "slot": "3"
            }
          ],
          "erc7201:openzeppelin.storage.ReentrancyGuard": [
            {
              "contract": "ReentrancyGuardUpgradeable",
              "label": "_status",
              "type": "t_uint256",
              "src": "@openzeppelin/contracts-upgradeable/utils/ReentrancyGuardUpgradeable.sol:40",
              "offset": 0,
              "slot": "0"
            }
          ],
          "erc7201:openzeppelin.storage.Ownable": [
            {
              "contract": "OwnableUpgradeable",
              "label": "_owner",
              "type": "t_address",
              "src": "@openzeppelin/contracts-upgradeable/access/OwnableUpgradeable.sol:24",
              "offset": 0,
              "slot": "0"
            }
          ],
          "erc7201:openzeppelin.storage.Initializable": [
            {
              "contract": "Initializable",
              "label": "_initialized",
              "type": "t_uint64",
              "src": "@openzeppelin/contracts-upgradeable/proxy/utils/Initializable.sol:69",
              "offset": 0,
              "slot": "0"
            },
            {
              "contract": "Initializable",
              "label": "_initializing",
              "type": "t_bool",
              "src": "@openzeppelin/contracts-upgradeable/proxy/utils/Initializable.sol:73",
              "offset": 8,
              "slot": "0"
            }
          ]
        }
      }
    },
    "f4b4c8ff2fdb50444e14e757f1c5d59b8837917426b43140e81ab08fbcdaf657": {
      "address": "0xcFaAFc21AD2FA114Cd76311B0F2377350a4AC499",
      "txHash": "0xa00e9a935ed98d7c10c281f5dc95988051d8de6570c605b6d01ea70f81a137ba",
      "layout": {
        "solcVersion": "0.8.23",
        "storage": [
          {
            "label": "isLongPool",
            "offset": 0,
            "slot": "0",
            "type": "t_bool",
            "contract": "BaseWasabiPool",
            "src": "contracts/BaseWasabiPool.sol:25"
          },
          {
            "label": "addressProvider",
            "offset": 1,
            "slot": "0",
            "type": "t_contract(IAddressProvider)11030",
            "contract": "BaseWasabiPool",
            "src": "contracts/BaseWasabiPool.sol:28"
          },
          {
            "label": "positions",
            "offset": 0,
            "slot": "1",
            "type": "t_mapping(t_uint256,t_bytes32)",
            "contract": "BaseWasabiPool",
            "src": "contracts/BaseWasabiPool.sol:31"
          },
          {
            "label": "vaults",
            "offset": 0,
            "slot": "2",
            "type": "t_mapping(t_address,t_address)",
            "contract": "BaseWasabiPool",
            "src": "contracts/BaseWasabiPool.sol:34"
          },
          {
            "label": "baseTokens",
            "offset": 0,
            "slot": "3",
            "type": "t_mapping(t_address,t_bool)",
            "contract": "BaseWasabiPool",
            "src": "contracts/BaseWasabiPool.sol:37"
          }
        ],
        "types": {
          "t_address": {
            "label": "address",
            "numberOfBytes": "20"
          },
          "t_bool": {
            "label": "bool",
            "numberOfBytes": "1"
          },
          "t_bytes32": {
            "label": "bytes32",
            "numberOfBytes": "32"
          },
          "t_string_storage": {
            "label": "string",
            "numberOfBytes": "32"
          },
          "t_struct(EIP712Storage)505_storage": {
            "label": "struct EIP712Upgradeable.EIP712Storage",
            "members": [
              {
                "label": "_hashedName",
                "type": "t_bytes32",
                "offset": 0,
                "slot": "0"
              },
              {
                "label": "_hashedVersion",
                "type": "t_bytes32",
                "offset": 0,
                "slot": "1"
              },
              {
                "label": "_name",
                "type": "t_string_storage",
                "offset": 0,
                "slot": "2"
              },
              {
                "label": "_version",
                "type": "t_string_storage",
                "offset": 0,
                "slot": "3"
              }
            ],
            "numberOfBytes": "128"
          },
          "t_struct(InitializableStorage)306_storage": {
            "label": "struct Initializable.InitializableStorage",
            "members": [
              {
                "label": "_initialized",
                "type": "t_uint64",
                "offset": 0,
                "slot": "0"
              },
              {
                "label": "_initializing",
                "type": "t_bool",
                "offset": 8,
                "slot": "0"
              }
            ],
            "numberOfBytes": "32"
          },
          "t_struct(OwnableStorage)14_storage": {
            "label": "struct OwnableUpgradeable.OwnableStorage",
            "members": [
              {
                "label": "_owner",
                "type": "t_address",
                "offset": 0,
                "slot": "0"
              }
            ],
            "numberOfBytes": "32"
          },
          "t_struct(ReentrancyGuardStorage)453_storage": {
            "label": "struct ReentrancyGuardUpgradeable.ReentrancyGuardStorage",
            "members": [
              {
                "label": "_status",
                "type": "t_uint256",
                "offset": 0,
                "slot": "0"
              }
            ],
            "numberOfBytes": "32"
          },
          "t_uint256": {
            "label": "uint256",
            "numberOfBytes": "32"
          },
          "t_uint64": {
            "label": "uint64",
            "numberOfBytes": "8"
          },
          "t_contract(IAddressProvider)11030": {
            "label": "contract IAddressProvider",
            "numberOfBytes": "20"
          },
          "t_mapping(t_address,t_address)": {
            "label": "mapping(address => address)",
            "numberOfBytes": "32"
          },
          "t_mapping(t_address,t_bool)": {
            "label": "mapping(address => bool)",
            "numberOfBytes": "32"
          },
          "t_mapping(t_uint256,t_bytes32)": {
            "label": "mapping(uint256 => bytes32)",
            "numberOfBytes": "32"
          }
        },
        "namespaces": {
          "erc7201:openzeppelin.storage.EIP712": [
            {
              "contract": "EIP712Upgradeable",
              "label": "_hashedName",
              "type": "t_bytes32",
              "src": "@openzeppelin/contracts-upgradeable/utils/cryptography/EIP712Upgradeable.sol:39",
              "offset": 0,
              "slot": "0"
            },
            {
              "contract": "EIP712Upgradeable",
              "label": "_hashedVersion",
              "type": "t_bytes32",
              "src": "@openzeppelin/contracts-upgradeable/utils/cryptography/EIP712Upgradeable.sol:41",
              "offset": 0,
              "slot": "1"
            },
            {
              "contract": "EIP712Upgradeable",
              "label": "_name",
              "type": "t_string_storage",
              "src": "@openzeppelin/contracts-upgradeable/utils/cryptography/EIP712Upgradeable.sol:43",
              "offset": 0,
              "slot": "2"
            },
            {
              "contract": "EIP712Upgradeable",
              "label": "_version",
              "type": "t_string_storage",
              "src": "@openzeppelin/contracts-upgradeable/utils/cryptography/EIP712Upgradeable.sol:44",
              "offset": 0,
              "slot": "3"
            }
          ],
          "erc7201:openzeppelin.storage.ReentrancyGuard": [
            {
              "contract": "ReentrancyGuardUpgradeable",
              "label": "_status",
              "type": "t_uint256",
              "src": "@openzeppelin/contracts-upgradeable/utils/ReentrancyGuardUpgradeable.sol:40",
              "offset": 0,
              "slot": "0"
            }
          ],
          "erc7201:openzeppelin.storage.Ownable": [
            {
              "contract": "OwnableUpgradeable",
              "label": "_owner",
              "type": "t_address",
              "src": "@openzeppelin/contracts-upgradeable/access/OwnableUpgradeable.sol:24",
              "offset": 0,
              "slot": "0"
            }
          ],
          "erc7201:openzeppelin.storage.Initializable": [
            {
              "contract": "Initializable",
              "label": "_initialized",
              "type": "t_uint64",
              "src": "@openzeppelin/contracts-upgradeable/proxy/utils/Initializable.sol:69",
              "offset": 0,
              "slot": "0"
            },
            {
              "contract": "Initializable",
              "label": "_initializing",
              "type": "t_bool",
              "src": "@openzeppelin/contracts-upgradeable/proxy/utils/Initializable.sol:73",
              "offset": 8,
              "slot": "0"
            }
          ]
        }
      },
      "allAddresses": [
        "0xcFaAFc21AD2FA114Cd76311B0F2377350a4AC499",
        "0x5B075fddE5c2D42713007288A58E90090982727C",
        "0xad42546cbF451660712060dECFed020B7c9FB70f"
      ]
    },
    "5c4e41aa3ced98c0b740844be57557587e632404cd5e38c13a29951fdd16a4f8": {
      "address": "0x1CCAf14d6FC6e079609Df066a126C5d4A748368c",
      "txHash": "0x8425421d96a397297e93ecf76343f085a2925e501b086a2fb79b951ecf77ee57",
      "layout": {
        "solcVersion": "0.8.23",
        "storage": [
          {
            "label": "pool",
            "offset": 0,
            "slot": "0",
            "type": "t_contract(IWasabiPerps)11570",
            "contract": "WasabiVault",
            "src": "contracts/vaults/WasabiVault.sol:16"
          },
          {
            "label": "totalAssetValue",
            "offset": 0,
            "slot": "1",
            "type": "t_uint256",
            "contract": "WasabiVault",
            "src": "contracts/vaults/WasabiVault.sol:17"
          },
          {
            "label": "addressProvider",
            "offset": 0,
            "slot": "2",
            "type": "t_contract(IAddressProvider)13265",
            "contract": "WasabiVault",
            "src": "contracts/vaults/WasabiVault.sol:18"
          }
        ],
        "types": {
          "t_address": {
            "label": "address",
            "numberOfBytes": "20"
          },
          "t_bool": {
            "label": "bool",
            "numberOfBytes": "1"
          },
          "t_contract(IERC20)1199": {
            "label": "contract IERC20",
            "numberOfBytes": "20"
          },
          "t_mapping(t_address,t_mapping(t_address,t_uint256))": {
            "label": "mapping(address => mapping(address => uint256))",
            "numberOfBytes": "32"
          },
          "t_mapping(t_address,t_uint256)": {
            "label": "mapping(address => uint256)",
            "numberOfBytes": "32"
          },
          "t_string_storage": {
            "label": "string",
            "numberOfBytes": "32"
          },
          "t_struct(ERC20Storage)440_storage": {
            "label": "struct ERC20Upgradeable.ERC20Storage",
            "members": [
              {
                "label": "_balances",
                "type": "t_mapping(t_address,t_uint256)",
                "offset": 0,
                "slot": "0"
              },
              {
                "label": "_allowances",
                "type": "t_mapping(t_address,t_mapping(t_address,t_uint256))",
                "offset": 0,
                "slot": "1"
              },
              {
                "label": "_totalSupply",
                "type": "t_uint256",
                "offset": 0,
                "slot": "2"
              },
              {
                "label": "_name",
                "type": "t_string_storage",
                "offset": 0,
                "slot": "3"
              },
              {
                "label": "_symbol",
                "type": "t_string_storage",
                "offset": 0,
                "slot": "4"
              }
            ],
            "numberOfBytes": "160"
          },
          "t_struct(ERC4626Storage)533_storage": {
            "label": "struct ERC4626Upgradeable.ERC4626Storage",
            "members": [
              {
                "label": "_asset",
                "type": "t_contract(IERC20)1199",
                "offset": 0,
                "slot": "0"
              },
              {
                "label": "_underlyingDecimals",
                "type": "t_uint8",
                "offset": 20,
                "slot": "0"
              }
            ],
            "numberOfBytes": "32"
          },
          "t_struct(InitializableStorage)306_storage": {
            "label": "struct Initializable.InitializableStorage",
            "members": [
              {
                "label": "_initialized",
                "type": "t_uint64",
                "offset": 0,
                "slot": "0"
              },
              {
                "label": "_initializing",
                "type": "t_bool",
                "offset": 8,
                "slot": "0"
              }
            ],
            "numberOfBytes": "32"
          },
          "t_struct(OwnableStorage)14_storage": {
            "label": "struct OwnableUpgradeable.OwnableStorage",
            "members": [
              {
                "label": "_owner",
                "type": "t_address",
                "offset": 0,
                "slot": "0"
              }
            ],
            "numberOfBytes": "32"
          },
          "t_struct(ReentrancyGuardStorage)680_storage": {
            "label": "struct ReentrancyGuardUpgradeable.ReentrancyGuardStorage",
            "members": [
              {
                "label": "_status",
                "type": "t_uint256",
                "offset": 0,
                "slot": "0"
              }
            ],
            "numberOfBytes": "32"
          },
          "t_uint256": {
            "label": "uint256",
            "numberOfBytes": "32"
          },
          "t_uint64": {
            "label": "uint64",
            "numberOfBytes": "8"
          },
          "t_uint8": {
            "label": "uint8",
            "numberOfBytes": "1"
          },
          "t_contract(IAddressProvider)13265": {
            "label": "contract IAddressProvider",
            "numberOfBytes": "20"
          },
          "t_contract(IWasabiPerps)11570": {
            "label": "contract IWasabiPerps",
            "numberOfBytes": "20"
          }
        },
        "namespaces": {
          "erc7201:openzeppelin.storage.ReentrancyGuard": [
            {
              "contract": "ReentrancyGuardUpgradeable",
              "label": "_status",
              "type": "t_uint256",
              "src": "@openzeppelin/contracts-upgradeable/utils/ReentrancyGuardUpgradeable.sol:40",
              "offset": 0,
              "slot": "0"
            }
          ],
          "erc7201:openzeppelin.storage.ERC4626": [
            {
              "contract": "ERC4626Upgradeable",
              "label": "_asset",
              "type": "t_contract(IERC20)1199",
              "src": "@openzeppelin/contracts-upgradeable/token/ERC20/extensions/ERC4626Upgradeable.sol:56",
              "offset": 0,
              "slot": "0"
            },
            {
              "contract": "ERC4626Upgradeable",
              "label": "_underlyingDecimals",
              "type": "t_uint8",
              "src": "@openzeppelin/contracts-upgradeable/token/ERC20/extensions/ERC4626Upgradeable.sol:57",
              "offset": 20,
              "slot": "0"
            }
          ],
          "erc7201:openzeppelin.storage.Ownable": [
            {
              "contract": "OwnableUpgradeable",
              "label": "_owner",
              "type": "t_address",
              "src": "@openzeppelin/contracts-upgradeable/access/OwnableUpgradeable.sol:24",
              "offset": 0,
              "slot": "0"
            }
          ],
          "erc7201:openzeppelin.storage.ERC20": [
            {
              "contract": "ERC20Upgradeable",
              "label": "_balances",
              "type": "t_mapping(t_address,t_uint256)",
              "src": "@openzeppelin/contracts-upgradeable/token/ERC20/ERC20Upgradeable.sol:38",
              "offset": 0,
              "slot": "0"
            },
            {
              "contract": "ERC20Upgradeable",
              "label": "_allowances",
              "type": "t_mapping(t_address,t_mapping(t_address,t_uint256))",
              "src": "@openzeppelin/contracts-upgradeable/token/ERC20/ERC20Upgradeable.sol:40",
              "offset": 0,
              "slot": "1"
            },
            {
              "contract": "ERC20Upgradeable",
              "label": "_totalSupply",
              "type": "t_uint256",
              "src": "@openzeppelin/contracts-upgradeable/token/ERC20/ERC20Upgradeable.sol:42",
              "offset": 0,
              "slot": "2"
            },
            {
              "contract": "ERC20Upgradeable",
              "label": "_name",
              "type": "t_string_storage",
              "src": "@openzeppelin/contracts-upgradeable/token/ERC20/ERC20Upgradeable.sol:44",
              "offset": 0,
              "slot": "3"
            },
            {
              "contract": "ERC20Upgradeable",
              "label": "_symbol",
              "type": "t_string_storage",
              "src": "@openzeppelin/contracts-upgradeable/token/ERC20/ERC20Upgradeable.sol:45",
              "offset": 0,
              "slot": "4"
            }
          ],
          "erc7201:openzeppelin.storage.Initializable": [
            {
              "contract": "Initializable",
              "label": "_initialized",
              "type": "t_uint64",
              "src": "@openzeppelin/contracts-upgradeable/proxy/utils/Initializable.sol:69",
              "offset": 0,
              "slot": "0"
            },
            {
              "contract": "Initializable",
              "label": "_initializing",
              "type": "t_bool",
              "src": "@openzeppelin/contracts-upgradeable/proxy/utils/Initializable.sol:73",
              "offset": 8,
              "slot": "0"
            }
          ]
        }
      }
    },
    "f4f7ff5faba5c969e046e7e19f12d25fe10fc0b34151dcd5d7cf661e35f4bad3": {
      "address": "0x9fd1b78f12BeDa905D9A4f0158849e9acc117563",
      "txHash": "0x002853061e7b63d401d5e011c45caa697f92fc8f199f8b7a9c57d916d3c90c2d",
      "layout": {
        "solcVersion": "0.8.23",
        "storage": [
          {
            "label": "isLongPool",
            "offset": 0,
            "slot": "0",
            "type": "t_bool",
            "contract": "BaseWasabiPool",
            "src": "contracts/BaseWasabiPool.sol:25"
          },
          {
            "label": "addressProvider",
            "offset": 1,
            "slot": "0",
            "type": "t_contract(IAddressProvider)11030",
            "contract": "BaseWasabiPool",
            "src": "contracts/BaseWasabiPool.sol:28"
          },
          {
            "label": "positions",
            "offset": 0,
            "slot": "1",
            "type": "t_mapping(t_uint256,t_bytes32)",
            "contract": "BaseWasabiPool",
            "src": "contracts/BaseWasabiPool.sol:31"
          },
          {
            "label": "vaults",
            "offset": 0,
            "slot": "2",
            "type": "t_mapping(t_address,t_address)",
            "contract": "BaseWasabiPool",
            "src": "contracts/BaseWasabiPool.sol:34"
          },
          {
            "label": "baseTokens",
            "offset": 0,
            "slot": "3",
            "type": "t_mapping(t_address,t_bool)",
            "contract": "BaseWasabiPool",
            "src": "contracts/BaseWasabiPool.sol:37"
          }
        ],
        "types": {
          "t_address": {
            "label": "address",
            "numberOfBytes": "20"
          },
          "t_bool": {
            "label": "bool",
            "numberOfBytes": "1"
          },
          "t_bytes32": {
            "label": "bytes32",
            "numberOfBytes": "32"
          },
          "t_string_storage": {
            "label": "string",
            "numberOfBytes": "32"
          },
          "t_struct(EIP712Storage)505_storage": {
            "label": "struct EIP712Upgradeable.EIP712Storage",
            "members": [
              {
                "label": "_hashedName",
                "type": "t_bytes32",
                "offset": 0,
                "slot": "0"
              },
              {
                "label": "_hashedVersion",
                "type": "t_bytes32",
                "offset": 0,
                "slot": "1"
              },
              {
                "label": "_name",
                "type": "t_string_storage",
                "offset": 0,
                "slot": "2"
              },
              {
                "label": "_version",
                "type": "t_string_storage",
                "offset": 0,
                "slot": "3"
              }
            ],
            "numberOfBytes": "128"
          },
          "t_struct(InitializableStorage)306_storage": {
            "label": "struct Initializable.InitializableStorage",
            "members": [
              {
                "label": "_initialized",
                "type": "t_uint64",
                "offset": 0,
                "slot": "0"
              },
              {
                "label": "_initializing",
                "type": "t_bool",
                "offset": 8,
                "slot": "0"
              }
            ],
            "numberOfBytes": "32"
          },
          "t_struct(OwnableStorage)14_storage": {
            "label": "struct OwnableUpgradeable.OwnableStorage",
            "members": [
              {
                "label": "_owner",
                "type": "t_address",
                "offset": 0,
                "slot": "0"
              }
            ],
            "numberOfBytes": "32"
          },
          "t_struct(ReentrancyGuardStorage)453_storage": {
            "label": "struct ReentrancyGuardUpgradeable.ReentrancyGuardStorage",
            "members": [
              {
                "label": "_status",
                "type": "t_uint256",
                "offset": 0,
                "slot": "0"
              }
            ],
            "numberOfBytes": "32"
          },
          "t_uint256": {
            "label": "uint256",
            "numberOfBytes": "32"
          },
          "t_uint64": {
            "label": "uint64",
            "numberOfBytes": "8"
          },
          "t_contract(IAddressProvider)11030": {
            "label": "contract IAddressProvider",
            "numberOfBytes": "20"
          },
          "t_mapping(t_address,t_address)": {
            "label": "mapping(address => address)",
            "numberOfBytes": "32"
          },
          "t_mapping(t_address,t_bool)": {
            "label": "mapping(address => bool)",
            "numberOfBytes": "32"
          },
          "t_mapping(t_uint256,t_bytes32)": {
            "label": "mapping(uint256 => bytes32)",
            "numberOfBytes": "32"
          }
        },
        "namespaces": {
          "erc7201:openzeppelin.storage.EIP712": [
            {
              "contract": "EIP712Upgradeable",
              "label": "_hashedName",
              "type": "t_bytes32",
              "src": "@openzeppelin/contracts-upgradeable/utils/cryptography/EIP712Upgradeable.sol:39",
              "offset": 0,
              "slot": "0"
            },
            {
              "contract": "EIP712Upgradeable",
              "label": "_hashedVersion",
              "type": "t_bytes32",
              "src": "@openzeppelin/contracts-upgradeable/utils/cryptography/EIP712Upgradeable.sol:41",
              "offset": 0,
              "slot": "1"
            },
            {
              "contract": "EIP712Upgradeable",
              "label": "_name",
              "type": "t_string_storage",
              "src": "@openzeppelin/contracts-upgradeable/utils/cryptography/EIP712Upgradeable.sol:43",
              "offset": 0,
              "slot": "2"
            },
            {
              "contract": "EIP712Upgradeable",
              "label": "_version",
              "type": "t_string_storage",
              "src": "@openzeppelin/contracts-upgradeable/utils/cryptography/EIP712Upgradeable.sol:44",
              "offset": 0,
              "slot": "3"
            }
          ],
          "erc7201:openzeppelin.storage.ReentrancyGuard": [
            {
              "contract": "ReentrancyGuardUpgradeable",
              "label": "_status",
              "type": "t_uint256",
              "src": "@openzeppelin/contracts-upgradeable/utils/ReentrancyGuardUpgradeable.sol:40",
              "offset": 0,
              "slot": "0"
            }
          ],
          "erc7201:openzeppelin.storage.Ownable": [
            {
              "contract": "OwnableUpgradeable",
              "label": "_owner",
              "type": "t_address",
              "src": "@openzeppelin/contracts-upgradeable/access/OwnableUpgradeable.sol:24",
              "offset": 0,
              "slot": "0"
            }
          ],
          "erc7201:openzeppelin.storage.Initializable": [
            {
              "contract": "Initializable",
              "label": "_initialized",
              "type": "t_uint64",
              "src": "@openzeppelin/contracts-upgradeable/proxy/utils/Initializable.sol:69",
              "offset": 0,
              "slot": "0"
            },
            {
              "contract": "Initializable",
              "label": "_initializing",
              "type": "t_bool",
              "src": "@openzeppelin/contracts-upgradeable/proxy/utils/Initializable.sol:73",
              "offset": 8,
              "slot": "0"
            }
          ]
        }
      }
    }
  }
}
