[
	{
		"address" : "0x8C7AC134ED985367EADC6F727d79E8295E11435c",
		"symbol" : "Kekec",
		"name" : "The Balkan Dwarf",
		"decimals" : 18,
		"image_url" : "https://wasabi-public.s3.amazonaws.com/tokens/KEKEC.png",
		"nft_address" : null,
		"pair_address" : "0xc6e40537215c1e041616478d8cfe312b1847b997",
		"mainnet_address" : "0x8C7AC134ED985367EADC6F727d79E8295E11435c",
		"max_leverage" : 3,
		"max_open_interest" : 12,
		"has_uni_v2" : 1,
		"nft_swap_enabled" : 0,
		"perp_enabled" : 0,
		"token_type" : "ERC20",
		"twitter_handle" : "@kekeceth",
		"max_short_principal" : null,
		"reverse" : 0
	}
]
